tests/__init__.py
tests/test_gtfsrealtimeparser.py
tests/test_servicestatusxmlparser.py
transiter_nycsubway/__init__.py
transiter_nycsubway/gtfsrealtimeparser.py
transiter_nycsubway/servicestatusxmlparser.py
transiter_nycsubway/stationscsvparser.py
transiter_nycsubway/gtfs/__init__.py
transiter_nycsubway/gtfs/gtfs_realtime_pb2.py
transiter_nycsubway/gtfs/nyct_subway_pb2.py
transiter_nycsubway-0.3.3.dist-info/LICENSE
transiter_nycsubway-0.3.3.dist-info/METADATA
transiter_nycsubway-0.3.3.dist-info/WHEEL
transiter_nycsubway-0.3.3.dist-info/top_level.txt
transiter_nycsubway-0.3.3.dist-info/RECORD
