Metadata-Version: 2.1
Name: transiter-nycsubway
Version: 0.3.3
Summary: NYC Subway integration for Transiter
Home-page: https://github.com/jamespfennell/transiter-nycsubway
Author: James Fennell
Author-email: jamespfennell@gmail.com
License: MIT
Platform: UNKNOWN
Requires-Dist: python-dateutil (>=2.8.1)
Requires-Dist: transiter (>=0.4.3)
